Workbook

Sheet Planilha3
A1: QTD | B1: (Vários itens)
A3: Fornecedor | B3: Filial_a_entregar | C3: Filial_cobranca | D3: Filial_a_faturar
A4: CIMASA IND. COMER.BRNDES | E4: ="UPDATE FORNECEDORES SET FILIAL_A_ENTREGAR = '"&B4&"', FILIAL_COBRANCA = '"&C4&"', FILIAL_A_FATURAR = '"&D4&"' WHERE FORNECEDOR = '"&A4&"'" -> UPDATE FORNECEDORES SET FILIAL_A_ENTREGAR = '', FILIAL_COBRANCA = '', FILIAL_A_FATURAR = '' WHERE FORNECEDOR = ' CIMASA IND. COMER.BRNDES'
A5: INFINIT SOLUCOES | B5: AVANTI- ADM C.CREDITO | C5: AVANTI- ADM C.CREDITO | D5: AVANTI- ADM C.CREDITO | E5: ="UPDATE FORNECEDORES SET FILIAL_A_ENTREGAR = '"&B5&"', FILIAL_COBRANCA = '"&C5&"', FILIAL_A_FATURAR = '"&D5&"' WHERE FORNECEDOR = '"&A5&"'" -> UPDATE FORNECEDORES SET FILIAL_A_ENTREGAR = 'AVANTI- ADM C.CREDITO', FILIAL_COBRANCA = 'AVANTI- ADM C.CREDITO', FILIAL_A_FATURAR = 'AVANTI- ADM C.CREDITO' WHERE FORNECEDOR = ' INFINIT SOLUCOES'
A6: M2 SERVICOS ELETRICOS | B6: ANPPLA | C6: ANPPLA | D6: ANPPLA | E6: ="UPDATE FORNECEDORES SET FILIAL_A_ENTREGAR = '"&B6&"', FILIAL_COBRANCA = '"&C6&"', FILIAL_A_FATURAR = '"&D6&"' WHERE FORNECEDOR = '"&A6&"'" -> UPDATE FORNECEDORES SET FILIAL_A_ENTREGAR = 'ANPPLA', FILIAL_COBRANCA = 'ANPPLA', FILIAL_A_FATURAR = 'ANPPLA' WHERE FORNECEDOR = ' M2 SERVICOS ELETRICOS'
A7: 3 PONTO 1 | B7: CD REGIS | C7: TATUAPE | D7: CD REGIS | E7: ="UPDATE FORNECEDORES SET FILIAL_A_ENTREGAR = '"&B7&"', FILIAL_COBRANCA = '"&C7&"', FILIAL_A_FATURAR = '"&D7&"' WHERE FORNECEDOR = '"&A7&"'" -> UPDATE FORNECEDORES SET FILIAL_A_ENTREGAR = 'CD REGIS', FILIAL_COBRANCA = 'TATUAPE', FILIAL_A_FATURAR = 'CD REGIS' WHERE FORNECEDOR = '3 PONTO 1'
A8: A J C TELE INFORMATICA | B8: CD REGIS | C8: CD REGIS | D8: CD REGIS | E8: ="UPDATE FORNECEDORES SET FILIAL_A_ENTREGAR = '"&B8&"', FILIAL_COBRANCA = '"&C8&"', FILIAL_A_FATURAR = '"&D8&"' WHERE FORNECEDOR = '"&A8&"'" -> UPDATE FORNECEDORES SET FILIAL_A_ENTREGAR = 'CD REGIS', FILIAL_COBRANCA = 'CD REGIS', FILIAL_A_FATURAR = 'CD REGIS' WHERE FORNECEDOR = 'A J C TELE INFORMATICA'
A9: A MICHELOTTI AK COM CONF | B9: CD REGIS | C9: CD REGIS | D9: CD REGIS | E9: ="UPDATE FORNECEDORES SET FILIAL_A_ENTREGAR = '"&B9&"', FILIAL_COBRANCA = '"&C9&"', FILIAL_A_FATURAR = '"&D9&"' WHERE FORNECEDOR = '"&A9&"'" -> UPDATE FORNECEDORES SET FILIAL_A_ENTREGAR = 'CD REGIS', FILIAL_COBRANCA = 'CD REGIS', FILIAL_A_FATURAR = 'CD REGIS' WHERE FORNECEDOR = 'A MICHELOTTI AK COM CONF'
A10: A.R.S COMERCIO DE ROUPAS | B10: CD REGIS | C10: CD REGIS | D10: CD REGIS | E10: ="UPDATE FORNECEDORES SET FILIAL_A_ENTREGAR = '"&B10&"', FILIAL_COBRANCA = '"&C10&"', FILIAL_A_FATURAR = '"&D10&"' WHERE FORNECEDOR = '"&A10&"'" -> UPDATE FORNECEDORES SET FILIAL_A_ENTREGAR = 'CD REGIS', FILIAL_COBRANCA = 'CD REGIS', FILIAL_A_FATURAR = 'CD REGIS' WHERE FORNECEDOR = 'A.R.S COMERCIO DE ROUPAS'
A11: ABB INFORMATICA | B11: MATRIZ | C11: MATRIZ | D11: MATRIZ | E11: ="UPDATE FORNECEDORES SET FILIAL_A_ENTREGAR = '"&B11&"', FILIAL_COBRANCA = '"&C11&"', FILIAL_A_FATURAR = '"&D11&"' WHERE FORNECEDOR = '"&A11&"'" -> UPDATE FORNECEDORES SET FILIAL_A_ENTREGAR = 'MATRIZ', FILIAL_COBRANCA = 'MATRIZ', FILIAL_A_FATURAR = 'MATRIZ' WHERE FORNECEDOR = 'ABB INFORMATICA'
A12: ACALANTO TRICOT | B12: CD REGIS | C12: TATUAPE | D12: CD REGIS | E12: ="UPDATE FORNECEDORES SET FILIAL_A_ENTREGAR = '"&B12&"', FILIAL_COBRANCA = '"&C12&"', FILIAL_A_FATURAR = '"&D12&"' WHERE FORNECEDOR = '"&A12&"'" -> UPDATE FORNECEDORES SET FILIAL_A_ENTREGAR = 'CD REGIS', FILIAL_COBRANCA = 'TATUAPE', FILIAL_A_FATURAR = 'CD REGIS' WHERE FORNECEDOR = 'ACALANTO TRICOT'
A13: ACAO INFORMATICA | B13: MATRIZ | C13: MATRIZ | D13: MATRIZ | E13: ="UPDATE FORNECEDORES SET FILIAL_A_ENTREGAR = '"&B13&"', FILIAL_COBRANCA = '"&C13&"', FILIAL_A_FATURAR = '"&D13&"' WHERE FORNECEDOR = '"&A13&"'" -> UPDATE FORNECEDORES SET FILIAL_A_ENTREGAR = 'MATRIZ', FILIAL_COBRANCA = 'MATRIZ', FILIAL_A_FATURAR = 'MATRIZ' WHERE FORNECEDOR = 'ACAO INFORMATICA'
A14: AÇÃO INFORMATICA BRASIL | B14: MATRIZ | C14: MATRIZ | D14: MATRIZ | E14: ="UPDATE FORNECEDORES SET FILIAL_A_ENTREGAR = '"&B14&"', FILIAL_COBRANCA = '"&C14&"', FILIAL_A_FATURAR = '"&D14&"' WHERE FORNECEDOR = '"&A14&"'" -> UPDATE FORNECEDORES SET FILIAL_A_ENTREGAR = 'MATRIZ', FILIAL_COBRANCA = 'MATRIZ', FILIAL_A_FATURAR = 'MATRIZ' WHERE FORNECEDOR = 'AÇÃO INFORMATICA BRASIL'
A15: ACESSO DIGITAL TECN | B15: AVANTI- ADM C.CREDITO | C15: AVANTI- ADM C.CREDITO | D15: AVANTI- ADM C.CREDITO | E15: ="UPDATE FORNECEDORES SET FILIAL_A_ENTREGAR = '"&B15&"', FILIAL_COBRANCA = '"&C15&"', FILIAL_A_FATURAR = '"&D15&"' WHERE FORNECEDOR = '"&A15&"'" -> UPDATE FORNECEDORES SET FILIAL_A_ENTREGAR = 'AVANTI- ADM C.CREDITO', FILIAL_COBRANCA = 'AVANTI- ADM C.CREDITO', FILIAL_A_FATURAR = 'AVANTI- ADM C.CREDITO' WHERE FORNECEDOR = 'ACESSO DIGITAL TECN'
A16: ACIL TEXTIL | B16: CD ARAQUARI | C16: MATRIZ | D16: CD ARAQUARI | E16: ="UPDATE FORNECEDORES SET FILIAL_A_ENTREGAR = '"&B16&"', FILIAL_COBRANCA = '"&C16&"', FILIAL_A_FATURAR = '"&D16&"' WHERE FORNECEDOR = '"&A16&"'" -> UPDATE FORNECEDORES SET FILIAL_A_ENTREGAR = 'CD ARAQUARI', FILIAL_COBRANCA = 'MATRIZ', FILIAL_A_FATURAR = 'CD ARAQUARI' WHERE FORNECEDOR = 'ACIL TEXTIL'
... A797: ZOTTIS IND. COM. E IMPORT | B797: CD REGIS | C797: TATUAPE | D797: CD REGIS | E797: ="UPDATE FORNECEDORES SET FILIAL_A_ENTREGAR = '"&B797&"', FILIAL_COBRANCA = '"&C797&"', FILIAL_A_FATURAR = '"&D797&"' WHERE FORNECEDOR = '"&A797&"'" -> UPDATE FORNECEDORES SET FILIAL_A_ENTREGAR = 'CD REGIS', FILIAL_COBRANCA = 'TATUAPE', FILIAL_A_FATURAR = 'CD REGIS' WHERE FORNECEDOR = 'ZOTTIS IND. COM. E IMPORT'
A798: Total Geral

Sheet FORNECEDOR
A1: Fornecedor | B1: QTD | C1: Filial_a_entregar | D1: Filial_cobranca | E1: Filial_a_faturar | F1: SQL
A2: ALLABARD | B2: =COUNTIF(PEDIDOS!$A:$A,FORNECEDOR!A2) -> 0 | C2: =INDEX(PEDIDOS!$A:$D,MATCH(FORNECEDOR!A2,PEDIDOS!$A:$A,0),2) -> #N/A | D2: =INDEX(PEDIDOS!$A:$D,MATCH(FORNECEDOR!A2,PEDIDOS!$A:$A,0),3) -> #N/A | E2: =INDEX(PEDIDOS!$A:$D,MATCH(FORNECEDOR!A2,PEDIDOS!$A:$A,0),4) -> #N/A
A3: CIMASA IND. COMER.BRNDES | B3: =COUNTIF(PEDIDOS!$A:$A,FORNECEDOR!A3) -> 1 | C3: =INDEX(PEDIDOS!$A:$D,MATCH(FORNECEDOR!A3,PEDIDOS!$A:$A,0),2) -> CD REGIS | D3: =INDEX(PEDIDOS!$A:$D,MATCH(FORNECEDOR!A3,PEDIDOS!$A:$A,0),3) -> CD REGIS | E3: =INDEX(PEDIDOS!$A:$D,MATCH(FORNECEDOR!A3,PEDIDOS!$A:$A,0),4) -> CD REGIS
A4: INFINIT SOLUCOES | B4: =COUNTIF(PEDIDOS!$A:$A,FORNECEDOR!A4) -> 1 | C4: =INDEX(PEDIDOS!$A:$D,MATCH(FORNECEDOR!A4,PEDIDOS!$A:$A,0),2) -> AVANTI- ADM C.CREDITO | D4: =INDEX(PEDIDOS!$A:$D,MATCH(FORNECEDOR!A4,PEDIDOS!$A:$A,0),3) -> AVANTI- ADM C.CREDITO | E4: =INDEX(PEDIDOS!$A:$D,MATCH(FORNECEDOR!A4,PEDIDOS!$A:$A,0),4) -> AVANTI- ADM C.CREDITO
A5: M2 SERVICOS ELETRICOS | B5: =COUNTIF(PEDIDOS!$A:$A,FORNECEDOR!A5) -> 3 | C5: =INDEX(PEDIDOS!$A:$D,MATCH(FORNECEDOR!A5,PEDIDOS!$A:$A,0),2) -> ANPPLA | D5: =INDEX(PEDIDOS!$A:$D,MATCH(FORNECEDOR!A5,PEDIDOS!$A:$A,0),3) -> ANPPLA | E5: =INDEX(PEDIDOS!$A:$D,MATCH(FORNECEDOR!A5,PEDIDOS!$A:$A,0),4) -> ANPPLA
A6: MARIA JOSE PINTO | B6: =COUNTIF(PEDIDOS!$A:$A,FORNECEDOR!A6) -> 0 | C6: =INDEX(PEDIDOS!$A:$D,MATCH(FORNECEDOR!A6,PEDIDOS!$A:$A,0),2) -> #N/A | D6: =INDEX(PEDIDOS!$A:$D,MATCH(FORNECEDOR!A6,PEDIDOS!$A:$A,0),3) -> #N/A | E6: =INDEX(PEDIDOS!$A:$D,MATCH(FORNECEDOR!A6,PEDIDOS!$A:$A,0),4) -> #N/A
A7: REINALDO BATISTA DA SILV | B7: =COUNTIF(PEDIDOS!$A:$A,FORNECEDOR!A7) -> 0 | C7: =INDEX(PEDIDOS!$A:$D,MATCH(FORNECEDOR!A7,PEDIDOS!$A:$A,0),2) -> #N/A | D7: =INDEX(PEDIDOS!$A:$D,MATCH(FORNECEDOR!A7,PEDIDOS!$A:$A,0),3) -> #N/A | E7: =INDEX(PEDIDOS!$A:$D,MATCH(FORNECEDOR!A7,PEDIDOS!$A:$A,0),4) -> #N/A
A8: 100NEXO | B8: =COUNTIF(PEDIDOS!$A:$A,FORNECEDOR!A8) -> 0 | C8: =INDEX(PEDIDOS!$A:$D,MATCH(FORNECEDOR!A8,PEDIDOS!$A:$A,0),2) -> #N/A | D8: =INDEX(PEDIDOS!$A:$D,MATCH(FORNECEDOR!A8,PEDIDOS!$A:$A,0),3) -> #N/A | E8: =INDEX(PEDIDOS!$A:$D,MATCH(FORNECEDOR!A8,PEDIDOS!$A:$A,0),4) -> #N/A
A9: 3 PONTO 1 | B9: =COUNTIF(PEDIDOS!$A:$A,FORNECEDOR!A9) -> 1 | C9: =INDEX(PEDIDOS!$A:$D,MATCH(FORNECEDOR!A9,PEDIDOS!$A:$A,0),2) -> CD REGIS | D9: =INDEX(PEDIDOS!$A:$D,MATCH(FORNECEDOR!A9,PEDIDOS!$A:$A,0),3) -> TATUAPE | E9: =INDEX(PEDIDOS!$A:$D,MATCH(FORNECEDOR!A9,PEDIDOS!$A:$A,0),4) -> CD REGIS
A10: 4SERVERS TECHNOLOGIES | B10: =COUNTIF(PEDIDOS!$A:$A,FORNECEDOR!A10) -> 0 | C10: =INDEX(PEDIDOS!$A:$D,MATCH(FORNECEDOR!A10,PEDIDOS!$A:$A,0),2) -> #N/A | D10: =INDEX(PEDIDOS!$A:$D,MATCH(FORNECEDOR!A10,PEDIDOS!$A:$A,0),3) -> #N/A | E10: =INDEX(PEDIDOS!$A:$D,MATCH(FORNECEDOR!A10,PEDIDOS!$A:$A,0),4) -> #N/A
A11: A J C TELE INFORMATICA | B11: =COUNTIF(PEDIDOS!$A:$A,FORNECEDOR!A11) -> 2 | C11: =INDEX(PEDIDOS!$A:$D,MATCH(FORNECEDOR!A11,PEDIDOS!$A:$A,0),2) -> CD REGIS | D11: =INDEX(PEDIDOS!$A:$D,MATCH(FORNECEDOR!A11,PEDIDOS!$A:$A,0),3) -> CD REGIS | E11: =INDEX(PEDIDOS!$A:$D,MATCH(FORNECEDOR!A11,PEDIDOS!$A:$A,0),4) -> CD REGIS
A12: A M DE ANDRADE FILHO | B12: =COUNTIF(PEDIDOS!$A:$A,FORNECEDOR!A12) -> 0 | C12: =INDEX(PEDIDOS!$A:$D,MATCH(FORNECEDOR!A12,PEDIDOS!$A:$A,0),2) -> #N/A | D12: =INDEX(PEDIDOS!$A:$D,MATCH(FORNECEDOR!A12,PEDIDOS!$A:$A,0),3) -> #N/A | E12: =INDEX(PEDIDOS!$A:$D,MATCH(FORNECEDOR!A12,PEDIDOS!$A:$A,0),4) -> #N/A
A13: A MAIS IND E COM | B13: =COUNTIF(PEDIDOS!$A:$A,FORNECEDOR!A13) -> 0 | C13: =INDEX(PEDIDOS!$A:$D,MATCH(FORNECEDOR!A13,PEDIDOS!$A:$A,0),2) -> #N/A | D13: =INDEX(PEDIDOS!$A:$D,MATCH(FORNECEDOR!A13,PEDIDOS!$A:$A,0),3) -> #N/A | E13: =INDEX(PEDIDOS!$A:$D,MATCH(FORNECEDOR!A13,PEDIDOS!$A:$A,0),4) -> #N/A
... A2489: ZUBICK 2 | B2489: =COUNTIF(PEDIDOS!$A:$A,FORNECEDOR!A2489) -> 0 | C2489: =INDEX(PEDIDOS!$A:$D,MATCH(FORNECEDOR!A2489,PEDIDOS!$A:$A,0),2) -> #N/A | D2489: =INDEX(PEDIDOS!$A:$D,MATCH(FORNECEDOR!A2489,PEDIDOS!$A:$A,0),3) -> #N/A | E2489: =INDEX(PEDIDOS!$A:$D,MATCH(FORNECEDOR!A2489,PEDIDOS!$A:$A,0),4) -> #N/A

Sheet PEDIDOS
A1: Fornecedor | B1: Filial_a_entregar | C1: Filial_cobranca | D1: Filial_a_faturar
A2: CIMASA IND. COMER.BRNDES | B2: CD REGIS | C2: CD REGIS | D2: CD REGIS
A3: INFINIT SOLUCOES | B3: AVANTI- ADM C.CREDITO | C3: AVANTI- ADM C.CREDITO | D3: AVANTI- ADM C.CREDITO
A4: M2 SERVICOS ELETRICOS | B4: ANPPLA | C4: ANPPLA | D4: ANPPLA
A5: M2 SERVICOS ELETRICOS | B5: JUNDIAI | C5: JUNDIAI | D5: JUNDIAI
A6: M2 SERVICOS ELETRICOS | B6: REGISTRO | C6: REGISTRO | D6: REGISTRO
A7: 3 PONTO 1 | B7: CD REGIS | C7: TATUAPE | D7: CD REGIS
A8: A J C TELE INFORMATICA | B8: CD REGIS | C8: CD REGIS | D8: CD REGIS
A9: A J C TELE INFORMATICA | B9: MATRIZ | C9: MATRIZ | D9: MATRIZ
A10: A MICHELOTTI AK COM CONF | B10: CD REGIS | C10: CD REGIS | D10: CD REGIS
A11: A.R.S COMERCIO DE ROUPAS | B11: CD REGIS | C11: CD REGIS | D11: CD REGIS
A12: ABB INFORMATICA | B12: MATRIZ | C12: MATRIZ | D12: MATRIZ
... A1618: ZOTTIS IND. COM. E IMPORT | B1618: CD REGIS | C1618: TATUAPE | D1618: CD REGIS
